{"cameraMode":{"drawMode":0,"name":"Shaded","section":"Shading Mode"},"sceneLighting":false,"audioPlay":false,"sceneViewState":{"m_AlwaysRefresh":false,"showFog":true,"showSkybox":false,"showFlares":true,"showImageEffects":true,"showParticleSystems":true,"showVisualEffectGraphs":true,"m_FxEnabled":true},"in2DMode":false,"pivot":{"x":2.392691135406494,"y":1.551708698272705,"z":8.152721405029297},"rotation":{"x":-0.04131193459033966,"y":-0.8517544269561768,"z":-0.06747709959745407,"w":0.5182137489318848},"size":0.31542688608169558,"orthographic":false}